{
  "model_name_or_path": "bert-base-uncased",
  "dataset_name": "squad",
  "do_train": 1,
  "do_eval": 1,
  "per_device_train_batch_size": 16,
  "max_seq_length": 384,
  "doc_stride": 128,
  "num_train_epochs": 10,
  "logging_steps": 500,
  "save_steps": 5000,
  "save_total_limit": 5,
  "seed": 17,
  "evaluation_strategy": "epoch",
  "learning_rate": 3e-5,
  "mask_scores_learning_rate": 1e-2,
  "output_dir": "output/squad_test",
  "logging_dir": "output/squad_test",
  "overwrite_cache": 0,
  "overwrite_output_dir": 1,
  "warmup_steps": 5400,
  "initial_warmup": 1,
  "final_warmup": 2,
  "initial_threshold": 1,
  "final_threshold": 0.3,
  "dense_pruning_method": "topK:1d",
  "dense_block_rows":1,
  "dense_block_cols":1,
  "attention_pruning_method": "topK",
  "attention_block_rows":64,
  "attention_block_cols":768,
  "ampere_pruning_method": "disabled",
  "mask_init": "constant",
  "mask_scale": 0.0
}
